rberga06/utils/__about__.py
rberga06/utils/about.py
rberga06/utils/cache.py
rberga06/utils/deps.py
rberga06/utils/func/dec.py
rberga06/utils/func/info.py
rberga06/utils/func/sig.py
rberga06/utils/func/wrap.py
rberga06/utils/imports.py
rberga06/utils/plugin/__init__.py
rberga06/utils/plugin/spec.py
rberga06/utils/plugin/system.py
rberga06/utils/types.py
rberga06_utils-0.0.1.dev3.dist-info/LICENSE
rberga06_utils-0.0.1.dev3.dist-info/METADATA
rberga06_utils-0.0.1.dev3.dist-info/WHEEL
rberga06_utils-0.0.1.dev3.dist-info/RECORD
