Metadata-Version: 2.1
Name: rberga06-utils
Version: 0.0.1.dev3
Summary: Useful utilities for Python projects.
Author: RBerga06
Author-email: 78449715+RBerga06@users.noreply.github.com
Requires-Python: >=3.11,<4.0
Classifier: Programming Language :: Python :: 3
Classifier: Programming Language :: Python :: 3.11
Requires-Dist: packaging (>=23.1,<24.0)
Requires-Dist: pydantic (>=2.0b2,<3.0)
Requires-Dist: pyyaml (>=6.0,<7.0)
Requires-Dist: typing-extensions (>=4.6.3,<5.0.0)
